[
    {
        "player": "Garagentor-Blackrock",
        "date": "19/11/23",
        "time": "19:33:44",
        "id": "1700415224-2",
        "itemID": 207788,
        "itemString": "item:207788::::::::70:72::3:6:6652:7979:9563:10247:1494:8767",
        "response": "Upgrade",
        "votes": 0,
        "class": "EVOKER",
        "instance": "Amirdrassil, the Dream's Hope-Heroic",
        "boss": "Fyrakk the Blazing",
        "gear1": "[Nasz'uro, the Unbound Legacy]",
        "gear2": "[Frigid Conservator's Implement]",
        "responseID": "1",
        "isAwardReason": "false",
        "rollType": "normal",
        "subType": "One-Handed Maces",
        "equipLoc": "One-Hand",
        "note": "absolut bis",
        "owner": "Wojer-Blackrock",
        "itemName": "Vakash, the Shadowed Inferno"
    },
    {
        "player": "Garagentor-Blackrock",
        "date": "19/11/23",
        "time": "22:32:37",
        "id": "1700425957-2",
        "itemID": 207146,
        "itemString": "item:207146::::::::70:72::5:7:6652:9516:9508:7980:9569:1501:8767",
        "response": "Upgrade",
        "votes": 0,
        "class": "EVOKER",
        "instance": "Amirdrassil, the Dream's Hope-Heroic",
        "boss": "Volcoross",
        "gear1": "[Flame-Touched Chain |A:Professions-ChatIcon-Quality-Tier5:17:17::1|a]",
        "gear2": "",
        "responseID": "1",
        "isAwardReason": "false",
        "rollType": "normal",
        "subType": "Mail",
        "equipLoc": "Waist",
        "note": "",
        "owner": "Wojer-Blackrock",
        "itemName": "Jeweled Sash of the Viper"
    },
    {
        "player": "Smalificent-Blackrock",
        "date": "19/11/23",
        "time": "20:34:02",
        "id": "1700418842-15",
        "itemID": 207118,
        "itemString": "item:207118::::::::70:72::5:6:6652:9508:7980:9568:1498:8767",
        "response": "Upgrade",
        "votes": 0,
        "class": "PRIEST",
        "instance": "Amirdrassil, the Dream's Hope-Heroic",
        "boss": "Igira the Cruel",
        "gear1": "[Breeches of the Furnace Seraph]",
        "gear2": "",
        "responseID": "1",
        "isAwardReason": "false",
        "rollType": "normal",
        "subType": "Cloth",
        "equipLoc": "Legs",
        "note": "catalyst rohling",
        "owner": "Wojer-Blackrock",
        "itemName": "Elder's Volcanic Wrap"
    },
    {
        "player": "Smalificent-Blackrock",
        "date": "19/11/23",
        "time": "22:34:26",
        "id": "1700426066-4",
        "itemID": 207122,
        "itemString": "item:207122::::::::70:72::5:6:6652:9508:7980:9569:1501:8767",
        "response": "Upgrade",
        "votes": 0,
        "class": "PRIEST",
        "instance": "Amirdrassil, the Dream's Hope-Heroic",
        "boss": "Volcoross",
        "gear1": "[Slippers of Heedless Sacrifice]",
        "gear2": "",
        "responseID": "1",
        "isAwardReason": "false",
        "rollType": "normal",
        "subType": "Cloth",
        "equipLoc": "Feet",
        "note": "LOW PRIO - CATALYST - 1,3%",
        "owner": "Wojer-Blackrock",
        "itemName": "Lost Scholar's Belted Treads"
    },
    {
        "player": "Zedarí-Blackrock",
        "date": "19/11/23",
        "time": "19:37:17",
        "id": "1700415437-6",
        "itemID": 210947,
        "itemString": "item:210947::::::::70:72::3:3:7979:1494:8767",
        "response": "Upgrade",
        "votes": 0,
        "class": "HUNTER",
        "instance": "Amirdrassil, the Dream's Hope-Heroic",
        "boss": "Fyrakk the Blazing",
        "gear1": "[Ashen Predator's Faceguard]",
        "gear2": "[Ashen Predator's Sling Vest]",
        "responseID": "1",
        "isAwardReason": "false",
        "rollType": "normal",
        "subType": "Context Token",
        "equipLoc": "",
        "note": "2er mit cata",
        "owner": "Wojer-Blackrock",
        "itemName": "Flame-Warped Curio"
    },
    {
        "player": "Neyfhi-Blackrock",
        "date": "19/11/23",
        "time": "20:35:07",
        "id": "1700418907-16",
        "itemID": 207162,
        "itemString": "item:207162::::::::70:72::5:6:6652:9599:7980:9568:1498:8767",
        "response": "Upgrade",
        "votes": 0,
        "class": "SHAMAN",
        "instance": "Amirdrassil, the Dream's Hope-Heroic",
        "boss": "Igira the Cruel",
        "gear1": "[Band of Twisted Bark]",
        "gear2": "[Band of the Wyrm Matron]",
        "responseID": "1",
        "isAwardReason": "false",
        "rollType": "normal",
        "subType": "Miscellaneous",
        "equipLoc": "Finger",
        "note": "",
        "owner": "Wojer-Blackrock",
        "itemName": "Signet of the Last Elder"
    },
    {
        "player": "Olympea-Blackrock",
        "date": "19/11/23",
        "time": "21:19:08",
        "id": "1700421548-24",
        "itemID": 207168,
        "itemString": "item:207168::::::::70:72::5:5:6652:7980:9569:1501:8767",
        "response": "Upgrade",
        "votes": 0,
        "class": "PRIEST",
        "instance": "Amirdrassil, the Dream's Hope-Heroic",
        "boss": "Council of Dreams",
        "gear1": "[Rashok's Molten Heart]",
        "gear2": "[Screaming Black Dragonscale]",
        "responseID": "1",
        "isAwardReason": "false",
        "rollType": "normal",
        "subType": "Miscellaneous",
        "equipLoc": "Trinket",
        "note": "BIS für holy und diszi",
        "owner": "Wojer-Blackrock",
        "itemName": "Pip's Emerald Friendship Badge"
    },
    {
        "player": "Sinå-Blackrock",
        "date": "19/11/23",
        "time": "19:50:08",
        "id": "1700416208-10",
        "itemID": 207160,
        "itemString": "item:207160::::::::70:72::5:6:6652:9508:7980:9568:1498:8767",
        "response": "Upgrade",
        "votes": 0,
        "class": "ROGUE",
        "instance": "Amirdrassil, the Dream's Hope-Heroic",
        "boss": "Gnarlroot",
        "gear1": "[Winter Forager's Cape]",
        "gear2": "",
        "responseID": "1",
        "isAwardReason": "false",
        "rollType": "normal",
        "subType": "Cloth",
        "equipLoc": "Back",
        "note": "crit versa vely good",
        "owner": "Wojer-Blackrock",
        "itemName": "Inflammable Drapeleaf"
    },
    {
        "player": "Sinå-Blackrock",
        "date": "19/11/23",
        "time": "20:37:36",
        "id": "1700419056-18",
        "itemID": 207165,
        "itemString": "item:207165::::::::70:72::5:5:6652:7980:9568:1498:8767",
        "response": "Upgrade",
        "votes": 0,
        "class": "ROGUE",
        "instance": "Amirdrassil, the Dream's Hope-Heroic",
        "boss": "Igira the Cruel",
        "gear1": "[Screaming Black Dragonscale]",
        "gear2": "[Elementium Pocket Anvil]",
        "responseID": "1",
        "isAwardReason": "false",
        "rollType": "normal",
        "subType": "Miscellaneous",
        "equipLoc": "Trinket",
        "note": "",
        "owner": "Wojer-Blackrock",
        "itemName": "Bandolier of Twisted Blades"
    },
    {
        "player": "Felmütze-Blackrock",
        "date": "19/11/23",
        "time": "20:35:36",
        "id": "1700418936-17",
        "itemID": 207131,
        "itemString": "item:207131::::::::70:72::5:7:6652:9599:9508:7980:9568:1498:8767",
        "response": "Upgrade",
        "votes": 0,
        "class": "DEMONHUNTER",
        "instance": "Amirdrassil, the Dream's Hope-Heroic",
        "boss": "Igira the Cruel",
        "gear1": "[Oblivion's Immortal Coil]",
        "gear2": "",
        "responseID": "1",
        "isAwardReason": "false",
        "rollType": "normal",
        "subType": "Leather",
        "equipLoc": "Waist",
        "note": "2,2%",
        "owner": "Wojer-Blackrock",
        "itemName": "Bloody Dragonhide Belt"
    },
    {
        "player": "Felmütze-Blackrock",
        "date": "19/11/23",
        "time": "21:12:58",
        "id": "1700421178-23",
        "itemID": 207784,
        "itemString": "item:207784::::::::70:72::5:6:6652:7980:9569:9418:1501:8767",
        "response": "Upgrade",
        "votes": 0,
        "class": "DEMONHUNTER",
        "instance": "Amirdrassil, the Dream's Hope-Heroic",
        "boss": "Council of Dreams",
        "gear1": "[Lightning Whelk Axe]",
        "gear2": "[Remnant Charglaive]",
        "responseID": "1",
        "isAwardReason": "false",
        "rollType": "normal",
        "subType": "Fist Weapons",
        "equipLoc": "One-Hand",
        "note": "6%",
        "owner": "Wojer-Blackrock",
        "itemName": "Thorncaller Claw"
    },
    {
        "player": "Rhiinfistn-Blackrock",
        "date": "19/11/23",
        "time": "19:31:39",
        "id": "1700415099-0",
        "itemID": 207174,
        "itemString": "item:207174::::::::70:72::3:5:6652:7979:9569:1501:8767",
        "response": "Upgrade",
        "votes": 0,
        "class": "MONK",
        "instance": "Amirdrassil, the Dream's Hope-Heroic",
        "boss": "Fyrakk the Blazing",
        "gear1": "[Prophetic Stonescales]",
        "gear2": "[Mark of Dargrul]",
        "responseID": "1",
        "isAwardReason": "false",
        "rollType": "normal",
        "subType": "Miscellaneous",
        "equipLoc": "Trinket",
        "note": "9,7% give",
        "owner": "Wojer-Blackrock",
        "itemName": "Fyrakk's Tainted Rageheart"
    },
    {
        "player": "Merith-Blackrock",
        "date": "19/11/23",
        "time": "19:33:49",
        "id": "1700415229-3",
        "itemID": 207786,
        "itemString": "item:207786::::::::70:72::3:6:6652:7979:9563:10247:1494:8767",
        "response": "Upgrade",
        "votes": 0,
        "class": "PALADIN",
        "instance": "Amirdrassil, the Dream's Hope-Heroic",
        "boss": "Fyrakk the Blazing",
        "gear1": "[Forgestorm]",
        "gear2": "[Primal Molten Defender |A:Professions-ChatIcon-Quality-Tier5:17:17::1|a]",
        "responseID": "1",
        "isAwardReason": "false",
        "rollType": "normal",
        "subType": "One-Handed Axes",
        "equipLoc": "One-Hand",
        "note": "9,1%",
        "owner": "Wojer-Blackrock",
        "itemName": "Gholak, the Final Conflagration"
    },
    {
        "player": "Merith-Blackrock",
        "date": "19/11/23",
        "time": "19:50:00",
        "id": "1700416200-9",
        "itemID": 207169,
        "itemString": "item:207169::::::::70:72::5:5:6652:7980:9568:1498:8767",
        "response": "Upgrade",
        "votes": 0,
        "class": "PALADIN",
        "instance": "Amirdrassil, the Dream's Hope-Heroic",
        "boss": "Gnarlroot",
        "gear1": "[Elementium Pocket Anvil]",
        "gear2": "[Gore-Crusted Butcher's Block]",
        "responseID": "1",
        "isAwardReason": "false",
        "rollType": "normal",
        "subType": "Miscellaneous",
        "equipLoc": "Trinket",
        "note": "7,6%",
        "owner": "Wojer-Blackrock",
        "itemName": "Branch of the Tormented Ancient"
    },
    {
        "player": "Merith-Blackrock",
        "date": "19/11/23",
        "time": "19:51:18",
        "id": "1700416278-13",
        "itemID": 207153,
        "itemString": "item:207153::::::::70:72::5:6:6652:9508:7980:9568:1498:8767",
        "response": "Upgrade",
        "votes": 0,
        "class": "PALADIN",
        "instance": "Amirdrassil, the Dream's Hope-Heroic",
        "boss": "Gnarlroot",
        "gear1": "[Heartfire Sentinel's Faulds]",
        "gear2": "",
        "responseID": "1",
        "isAwardReason": "false",
        "rollType": "normal",
        "subType": "Plate",
        "equipLoc": "Legs",
        "note": "",
        "owner": "Wojer-Blackrock",
        "itemName": "Seared Ironwood Greaves"
    },
    {
        "player": "Iysform-Blackrock",
        "date": "19/11/23",
        "time": "19:51:14",
        "id": "1700416274-12",
        "itemID": 207153,
        "itemString": "item:207153::::::::70:72::5:6:41:9508:7980:9568:1498:8767",
        "response": "Upgrade",
        "votes": 0,
        "class": "PALADIN",
        "instance": "Amirdrassil, the Dream's Hope-Heroic",
        "boss": "Gnarlroot",
        "gear1": "[Heartfire Sentinel's Faulds]",
        "gear2": "",
        "responseID": "1",
        "isAwardReason": "false",
        "rollType": "normal",
        "subType": "Plate",
        "equipLoc": "Legs",
        "note": "ggf set catalyst",
        "owner": "Wojer-Blackrock",
        "itemName": "Seared Ironwood Greaves"
    },
    {
        "player": "Plaguerunner-Blackrock",
        "date": "19/11/23",
        "time": "19:36:48",
        "id": "1700415408-5",
        "itemID": 210947,
        "itemString": "item:210947::::::::70:72::3:3:7979:1494:8767",
        "response": "Upgrade",
        "votes": 0,
        "class": "HUNTER",
        "instance": "Amirdrassil, the Dream's Hope-Heroic",
        "boss": "Fyrakk the Blazing",
        "gear1": "[Ashen Predator's Faceguard]",
        "gear2": "[Ashen Predator's Sling Vest]",
        "responseID": "1",
        "isAwardReason": "false",
        "rollType": "normal",
        "subType": "Context Token",
        "equipLoc": "",
        "note": "1st set item",
        "owner": "Wojer-Blackrock",
        "itemName": "Flame-Warped Curio"
    },
    {
        "player": "Wojer-Blackrock",
        "date": "19/11/23",
        "time": "22:30:44",
        "id": "1700425844-0",
        "itemID": 207152,
        "itemString": "item:207152::::::::70:72::5:6:6652:9508:7980:9569:1501:8767",
        "response": "Upgrade",
        "votes": 0,
        "class": "WARRIOR",
        "instance": "Amirdrassil, the Dream's Hope-Heroic",
        "boss": "Volcoross",
        "gear1": "[Pauldrons of the Onyx Crucible]",
        "gear2": "",
        "responseID": "1",
        "isAwardReason": "false",
        "rollType": "normal",
        "subType": "Plate",
        "equipLoc": "Shoulder",
        "note": "cata",
        "owner": "Wojer-Blackrock",
        "itemName": "Volcanic Spelunker's Vents"
    },
    {
        "player": "Wojer-Blackrock",
        "date": "19/11/23",
        "time": "22:34:33",
        "id": "1700426073-5",
        "itemID": 207789,
        "itemString": "item:207789::::::::70:72::5:5:6652:7980:9569:1501:8767",
        "response": "Off-Spec",
        "votes": 0,
        "class": "WARRIOR",
        "instance": "Amirdrassil, the Dream's Hope-Heroic",
        "boss": "Volcoross",
        "gear1": "[Ravencrest's Wrath]",
        "gear2": "[Ashkandur, Fall of the Brotherhood]",
        "responseID": "4",
        "isAwardReason": "false",
        "rollType": "normal",
        "subType": "One-Handed Swords",
        "equipLoc": "One-Hand",
        "note": "",
        "owner": "Wojer-Blackrock",
        "itemName": "Volcoross's Barbed Fang"
    },
    {
        "player": "Scammerin-Blackrock",
        "date": "19/11/23",
        "time": "20:31:38",
        "id": "1700418698-14",
        "itemID": 207783,
        "itemString": "item:207783::::::::70:72::5:5:6652:7980:9568:1498:8767",
        "response": "Upgrade",
        "votes": 0,
        "class": "ROGUE",
        "instance": "Amirdrassil, the Dream's Hope-Heroic",
        "boss": "Igira the Cruel",
        "gear1": "[Cruel Dreamcarver]",
        "gear2": "[Primal Molten Shortblade |A:Professions-ChatIcon-Quality-Tier5:17:17::1|a]",
        "responseID": "1",
        "isAwardReason": "false",
        "rollType": "normal",
        "subType": "Daggers",
        "equipLoc": "One-Hand",
        "note": "6,32",
        "owner": "Wojer-Blackrock",
        "itemName": "Cruel Dreamcarver"
    },
    {
        "player": "Gingaer-Blackrock",
        "date": "19/11/23",
        "time": "19:37:46",
        "id": "1700415466-7",
        "itemID": 207154,
        "itemString": "item:207154::::::::70:72::3:6:6652:9505:7979:9563:1494:8767",
        "response": "Upgrade",
        "votes": 0,
        "class": "DEATHKNIGHT",
        "instance": "Amirdrassil, the Dream's Hope-Heroic",
        "boss": "Fyrakk the Blazing",
        "gear1": "[Lingering Phantom's Plackart]",
        "gear2": "",
        "responseID": "1",
        "isAwardReason": "false",
        "rollType": "normal",
        "subType": "Plate",
        "equipLoc": "Chest",
        "note": "",
        "owner": "Wojer-Blackrock",
        "itemName": "Carapace of the Unbending Flame"
    },
    {
        "player": "Gingaer-Blackrock",
        "date": "19/11/23",
        "time": "22:30:52",
        "id": "1700425852-1",
        "itemID": 207148,
        "itemString": "item:207148::::::::70:72::5:6:6652:9508:7980:9569:1501:8767",
        "response": "Upgrade",
        "votes": 0,
        "class": "DEATHKNIGHT",
        "instance": "Amirdrassil, the Dream's Hope-Heroic",
        "boss": "Volcoross",
        "gear1": "[Lavaforged Sollerets]",
        "gear2": "",
        "responseID": "1",
        "isAwardReason": "false",
        "rollType": "normal",
        "subType": "Plate",
        "equipLoc": "Feet",
        "note": "1,5%",
        "owner": "Wojer-Blackrock",
        "itemName": "Lavaforged Sollerets"
    },
    {
        "player": "Arzuria-Blackrock",
        "date": "19/11/23",
        "time": "19:48:52",
        "id": "1700416132-8",
        "itemID": 207126,
        "itemString": "item:207126::::::::70:72::5:6:6652:9508:7980:9568:1498:8767",
        "response": "Upgrade",
        "votes": 0,
        "class": "MONK",
        "instance": "Amirdrassil, the Dream's Hope-Heroic",
        "boss": "Gnarlroot",
        "gear1": "[Slimy Expulsion Boots |A:Professions-ChatIcon-Quality-Tier5:17:17::1|a]",
        "gear2": "",
        "responseID": "1",
        "isAwardReason": "false",
        "rollType": "normal",
        "subType": "Leather",
        "equipLoc": "Feet",
        "note": "0.6",
        "owner": "Wojer-Blackrock",
        "itemName": "Twisted Blossom Stompers"
    },
    {
        "player": "Dbuff-Blackrock",
        "date": "19/11/23",
        "time": "19:33:40",
        "id": "1700415220-1",
        "itemID": 207788,
        "itemString": "item:207788::::::::70:72::3:6:6652:7979:9563:10247:1494:8767",
        "response": "Upgrade",
        "votes": 0,
        "class": "EVOKER",
        "instance": "Amirdrassil, the Dream's Hope-Heroic",
        "boss": "Fyrakk the Blazing",
        "gear1": "[Staff of Incandescent Torment]",
        "gear2": "",
        "responseID": "1",
        "isAwardReason": "false",
        "rollType": "normal",
        "subType": "One-Handed Maces",
        "equipLoc": "One-Hand",
        "note": "bis",
        "owner": "Wojer-Blackrock",
        "itemName": "Vakash, the Shadowed Inferno"
    },
    {
        "player": "Beefbote-Blackrock",
        "date": "19/11/23",
        "time": "21:11:55",
        "id": "1700421115-22",
        "itemID": 207139,
        "itemString": "item:207139::::::::70:72::5:6:6652:9508:7980:9569:1501:8767",
        "response": "Upgrade",
        "votes": 0,
        "class": "HUNTER",
        "instance": "Amirdrassil, the Dream's Hope-Heroic",
        "boss": "Council of Dreams",
        "gear1": "[Grunt's Eternal Treads]",
        "gear2": "",
        "responseID": "1",
        "isAwardReason": "false",
        "rollType": "normal",
        "subType": "Mail",
        "equipLoc": "Feet",
        "note": "",
        "owner": "Wojer-Blackrock",
        "itemName": "Cleats of the Savage Claw"
    },
    {
        "player": "Ravantyr-Blackrock",
        "date": "19/11/23",
        "time": "21:10:53",
        "id": "1700421053-21",
        "itemID": 207138,
        "itemString": "item:207138::::::::70:72::5:6:6652:9508:7980:9569:1501:8767",
        "response": "Upgrade",
        "votes": 0,
        "class": "EVOKER",
        "instance": "Amirdrassil, the Dream's Hope-Heroic",
        "boss": "Council of Dreams",
        "gear1": "[Chausses of Obsidian Secrets]",
        "gear2": "",
        "responseID": "1",
        "isAwardReason": "false",
        "rollType": "normal",
        "subType": "Mail",
        "equipLoc": "Legs",
        "note": "w[rde in setteil umwandeln",
        "owner": "Wojer-Blackrock",
        "itemName": "Aerwynn's Ritual Sarong"
    },
    {
        "player": "Oonah-Blackrock",
        "date": "19/11/23",
        "time": "20:38:38",
        "id": "1700419118-19",
        "itemID": 207468,
        "itemString": "item:207468::::::::70:72::5:4:9514:7980:1498:8767",
        "response": "Upgrade",
        "votes": 0,
        "class": "PRIEST",
        "instance": "Amirdrassil, the Dream's Hope-Heroic",
        "boss": "Igira the Cruel",
        "gear1": "[Grasp of the Furnace Seraph]",
        "gear2": "",
        "responseID": "1",
        "isAwardReason": "false",
        "rollType": "normal",
        "subType": "Junk",
        "equipLoc": "",
        "note": "erstes",
        "owner": "Wojer-Blackrock",
        "itemName": "Venerated Tormented Dreamheart"
    },
    {
        "player": "Pantlezz-Blackrock",
        "date": "19/11/23",
        "time": "19:34:56",
        "id": "1700415296-4",
        "itemID": 207132,
        "itemString": "item:207132::::::::70:72::3:6:6652:9505:7979:9563:1494:8767",
        "response": "Upgrade",
        "votes": 0,
        "class": "DRUID",
        "instance": "Amirdrassil, the Dream's Hope-Heroic",
        "boss": "Fyrakk the Blazing",
        "gear1": "[Life-Bound Trousers |A:Professions-ChatIcon-Quality-Tier5:17:17::1|a]",
        "gear2": "",
        "responseID": "1",
        "isAwardReason": "false",
        "rollType": "normal",
        "subType": "Leather",
        "equipLoc": "Legs",
        "note": "2.4",
        "owner": "Wojer-Blackrock",
        "itemName": "Frenzied Incarnate Legwraps"
    },
    {
        "player": "Pantlezz-Blackrock",
        "date": "19/11/23",
        "time": "22:33:29",
        "id": "1700426009-3",
        "itemID": 207130,
        "itemString": "item:207130::::::::70:72::5:6:6652:9508:7980:9569:1501:8767",
        "response": "Upgrade",
        "votes": 0,
        "class": "DRUID",
        "instance": "Amirdrassil, the Dream's Hope-Heroic",
        "boss": "Volcoross",
        "gear1": "[Handguards of the Autumn Blaze]",
        "gear2": "",
        "responseID": "1",
        "isAwardReason": "false",
        "rollType": "normal",
        "subType": "Leather",
        "equipLoc": "Hands",
        "note": "potenzieler 2er t bonus catayst",
        "owner": "Wojer-Blackrock",
        "itemName": "Flamewaker's Grips"
    },
    {
        "player": "Snusnuu-Blackrock",
        "date": "19/11/23",
        "time": "21:09:19",
        "id": "1700420959-20",
        "itemID": 207138,
        "itemString": "item:207138::::::::70:72::5:6:6652:9508:7980:9569:1501:8767",
        "response": "Upgrade",
        "votes": 0,
        "class": "SHAMAN",
        "instance": "Amirdrassil, the Dream's Hope-Heroic",
        "boss": "Council of Dreams",
        "gear1": "[Spirited Stag's Legguards]",
        "gear2": "",
        "responseID": "1",
        "isAwardReason": "false",
        "rollType": "normal",
        "subType": "Mail",
        "equipLoc": "Legs",
        "note": "4% und kommt in den Catalyst",
        "owner": "Wojer-Blackrock",
        "itemName": "Aerwynn's Ritual Sarong"
    },
    {
        "player": "Nirlendra-Blackrock",
        "date": "15/11/23",
        "time": "20:48:50",
        "id": "1700074130-16",
        "itemID": 207782,
        "itemString": "item:207782::::::::70:72::3:5:6652:7979:9561:1488:8767",
        "response": "Upgrade",
        "votes": 0,
        "class": "DRUID",
        "instance": "Amirdrassil, the Dream's Hope-Normal",
        "boss": "Council of Dreams",
        "gear1": "[Illuminating Pillar of the Isles |A:Professions-ChatIcon-Quality-Tier5:17:17::1|a]",
        "gear2": "",
        "responseID": "1",
        "isAwardReason": "false",
        "rollType": "normal",
        "subType": "Daggers",
        "equipLoc": "One-Hand",
        "note": "4,7%",
        "owner": "Wojer-Blackrock",
        "itemName": "Sickle of the White Stag"
    },
    {
        "player": "Neptunz-Blackrock",
        "date": "15/11/23",
        "time": "21:48:44",
        "id": "1700077724-35",
        "itemID": 207159,
        "itemString": "item:207159::::::::70:72::3:6:6652:9599:7979:9562:1491:8767",
        "response": "Upgrade",
        "votes": 0,
        "class": "DRUID",
        "instance": "Amirdrassil, the Dream's Hope-Normal",
        "boss": "Larodar, Keeper of the Flame",
        "gear1": "[Ring of Frozen Rain]",
        "gear2": "[Signet of Titanic Insight |A:Professions-ChatIcon-Quality-Tier5:17:17::1|a]",
        "responseID": "1",
        "isAwardReason": "false",
        "rollType": "normal",
        "subType": "Miscellaneous",
        "equipLoc": "Finger",
        "note": "2.5 %",
        "owner": "Wojer-Blackrock",
        "itemName": "Band of Burning Thorns"
    },
    {
        "player": "Smalificent-Blackrock",
        "date": "15/11/23",
        "time": "20:46:09",
        "id": "1700073969-13",
        "itemID": 207119,
        "itemString": "item:207119::::::::70:72::3:7:6652:9599:9505:7979:9561:1488:8767",
        "response": "Upgrade",
        "votes": 0,
        "class": "PRIEST",
        "instance": "Amirdrassil, the Dream's Hope-Normal",
        "boss": "Council of Dreams",
        "gear1": "[Sash of the Furnace Seraph]",
        "gear2": "",
        "responseID": "1",
        "isAwardReason": "false",
        "rollType": "normal",
        "subType": "Cloth",
        "equipLoc": "Waist",
        "note": "1,8",
        "owner": "Wojer-Blackrock",
        "itemName": "Urctos's Hibernal Dial"
    },
    {
        "player": "Keckbooy-Blackrock",
        "date": "15/11/23",
        "time": "20:31:21",
        "id": "1700073081-7",
        "itemID": 207118,
        "itemString": "item:207118::::::::70:72::3:6:6652:9505:7979:9560:1485:8767",
        "response": "Upgrade",
        "votes": 0,
        "class": "MAGE",
        "instance": "Amirdrassil, the Dream's Hope-Normal",
        "boss": "Igira the Cruel",
        "gear1": "[Underlight Conjurer's Trousers]",
        "gear2": "",
        "responseID": "1",
        "isAwardReason": "false",
        "rollType": "normal",
        "subType": "Cloth",
        "equipLoc": "Legs",
        "note": "Kann zu 2 set machen",
        "owner": "Wojer-Blackrock",
        "itemName": "Elder's Volcanic Wrap"
    },
    {
        "player": "Keckbooy-Blackrock",
        "date": "15/11/23",
        "time": "22:31:49",
        "id": "1700080309-49",
        "itemID": 207172,
        "itemString": "item:207172::::::::70:72::3:5:6652:7979:9563:1494:8767",
        "response": "Upgrade",
        "votes": 0,
        "class": "MAGE",
        "instance": "Amirdrassil, the Dream's Hope-Normal",
        "boss": "Tindral Sageswift, Seer of the Flame",
        "gear1": "[Spoils of Neltharus]",
        "gear2": "[Ominous Chromatic Essence]",
        "responseID": "1",
        "isAwardReason": "false",
        "rollType": "normal",
        "subType": "Miscellaneous",
        "equipLoc": "Trinket",
        "note": "5,5% upgrade",
        "owner": "Wojer-Blackrock",
        "itemName": "Belor'relos, the Suncaller"
    },
    {
        "player": "Zedarí-Blackrock",
        "date": "15/11/23",
        "time": "20:47:04",
        "id": "1700074024-14",
        "itemID": 207139,
        "itemString": "item:207139::::::::70:72::3:6:6652:9505:7979:9561:1488:8767",
        "response": "Upgrade",
        "votes": 0,
        "class": "HUNTER",
        "instance": "Amirdrassil, the Dream's Hope-Normal",
        "boss": "Council of Dreams",
        "gear1": "[Flame-Touched Treads |A:Professions-ChatIcon-Quality-Tier5:17:17::1|a]",
        "gear2": "",
        "responseID": "1",
        "isAwardReason": "false",
        "rollType": "normal",
        "subType": "Mail",
        "equipLoc": "Feet",
        "note": "2,4%",
        "owner": "Wojer-Blackrock",
        "itemName": "Cleats of the Savage Claw"
    },
    {
        "player": "Neyfhi-Blackrock",
        "date": "15/11/23",
        "time": "21:04:02",
        "id": "1700075042-21",
        "itemID": 210203,
        "itemString": "item:210203::::::::70:72::3:7:6652:9599:9505:7979:9562:1491:8767",
        "response": "Upgrade",
        "votes": 0,
        "class": "SHAMAN",
        "instance": "Amirdrassil, the Dream's Hope-Normal",
        "boss": "Nymue, Weaver of the Cycle",
        "gear1": "[Blighted Grasp Bracers]",
        "gear2": "",
        "responseID": "1",
        "isAwardReason": "false",
        "rollType": "normal",
        "subType": "Mail",
        "equipLoc": "Wrist",
        "note": "0,5% :D",
        "owner": "Wojer-Blackrock",
        "itemName": "Wellspring Wristlets"
    },
    {
        "player": "Wojer-Blackrock",
        "date": "15/11/23",
        "time": "20:24:59",
        "id": "1700072699-0",
        "itemID": 201740,
        "itemString": "item:201740::::::::70:72::3",
        "response": "Banking",
        "votes": 0,
        "class": "WARRIOR",
        "instance": "Amirdrassil, the Dream's Hope-Normal",
        "boss": "Igira the Cruel",
        "gear1": "",
        "gear2": "",
        "responseID": "2",
        "isAwardReason": "true",
        "rollType": "normal",
        "subType": "Alchemy",
        "equipLoc": "",
        "note": "",
        "owner": "Wojer-Blackrock",
        "itemName": "Elemental Codex of Ultimate Power"
    },
    {
        "player": "Wojer-Blackrock",
        "date": "15/11/23",
        "time": "20:25:59",
        "id": "1700072759-1",
        "itemID": 208427,
        "itemString": "item:208427::::::::70:577::3:6:6652:9505:7979:9561:1488:8767:1:28:2609",
        "response": "Banking",
        "votes": 0,
        "class": "WARRIOR",
        "instance": "Amirdrassil, the Dream's Hope-Normal",
        "boss": "Igira the Cruel",
        "gear1": "",
        "gear2": "",
        "responseID": "2",
        "isAwardReason": "true",
        "rollType": "normal",
        "subType": "Plate",
        "equipLoc": "Feet",
        "note": "",
        "owner": "Leftêr-Blackrock",
        "itemName": "Insurgent Flame Warboots"
    },
    {
        "player": "Wojer-Blackrock",
        "date": "15/11/23",
        "time": "21:02:12",
        "id": "1700074932-18",
        "itemID": 208428,
        "itemString": "item:208428::::::::70:266::3:6:6652:9505:7979:9561:1488:8767:1:28:2609",
        "response": "Banking",
        "votes": 0,
        "class": "WARRIOR",
        "instance": "Amirdrassil, the Dream's Hope-Normal",
        "boss": "Nymue, Weaver of the Cycle",
        "gear1": "",
        "gear2": "",
        "responseID": "2",
        "isAwardReason": "true",
        "rollType": "normal",
        "subType": "Mail",
        "equipLoc": "Shoulder",
        "note": "",
        "owner": "Mokielock-Blackrock",
        "itemName": "Mantle of Slumbering Sands"
    },
    {
        "player": "Wojer-Blackrock",
        "date": "15/11/23",
        "time": "21:03:30",
        "id": "1700075010-19",
        "itemID": 207155,
        "itemString": "item:207155::::::::70:72::3:6:6652:9505:7979:9562:1491:8767",
        "response": "Upgrade",
        "votes": 0,
        "class": "WARRIOR",
        "instance": "Amirdrassil, the Dream's Hope-Normal",
        "boss": "Nymue, Weaver of the Cycle",
        "gear1": "[Twisted Vision's Demigaunts]",
        "gear2": "",
        "responseID": "1",
        "isAwardReason": "false",
        "rollType": "normal",
        "subType": "Plate",
        "equipLoc": "Hands",
        "note": "1,8% wenn catalyst",
        "owner": "Wojer-Blackrock",
        "itemName": "Eldermoss Gauntlets"
    },
    {
        "player": "Wojer-Blackrock",
        "date": "15/11/23",
        "time": "22:03:59",
        "id": "1700078639-42",
        "itemID": 207166,
        "itemString": "item:207166::::::::70:72::3:5:6652:7979:9562:1491:8767",
        "response": "Upgrade",
        "votes": 0,
        "class": "WARRIOR",
        "instance": "Amirdrassil, the Dream's Hope-Normal",
        "boss": "Smolderon",
        "gear1": "[Rezan's Gleaming Eye]",
        "gear2": "[Mark of Dargrul]",
        "responseID": "1",
        "isAwardReason": "false",
        "rollType": "normal",
        "subType": "Miscellaneous",
        "equipLoc": "Trinket",
        "note": "5,3",
        "owner": "Wojer-Blackrock",
        "itemName": "Cataclysmic Signet Brand"
    },
    {
        "player": "Wojer-Blackrock",
        "date": "15/11/23",
        "time": "22:25:28",
        "id": "1700079928-43",
        "itemID": 210644,
        "itemString": "item:210644::::::::70:72::3",
        "response": "Banking",
        "votes": 0,
        "class": "WARRIOR",
        "instance": "Amirdrassil, the Dream's Hope-Normal",
        "boss": "Tindral Sageswift, Seer of the Flame",
        "gear1": "",
        "gear2": "",
        "responseID": "2",
        "isAwardReason": "true",
        "rollType": "normal",
        "subType": "Blacksmithing",
        "equipLoc": "",
        "note": "",
        "owner": "Wojer-Blackrock",
        "itemName": "Plans: Flourishing Dream Helm"
    },
    {
        "player": "Felmütze-Blackrock",
        "date": "15/11/23",
        "time": "20:28:29",
        "id": "1700072909-4",
        "itemID": 207466,
        "itemString": "item:207466::::::::70:72::3:4:9514:7979:1485:8767",
        "response": "Upgrade",
        "votes": 0,
        "class": "DEMONHUNTER",
        "instance": "Amirdrassil, the Dream's Hope-Normal",
        "boss": "Igira the Cruel",
        "gear1": "[Kinslayer's Bloodstained Grips]",
        "gear2": "",
        "responseID": "1",
        "isAwardReason": "false",
        "rollType": "normal",
        "subType": "Junk",
        "equipLoc": "",
        "note": "",
        "owner": "Wojer-Blackrock",
        "itemName": "Dreadful Tormented Dreamheart"
    },
    {
        "player": "Felmütze-Blackrock",
        "date": "15/11/23",
        "time": "22:00:50",
        "id": "1700078450-38",
        "itemID": 207791,
        "itemString": "item:207791::::::::70:72::3:5:6652:7979:9562:1491:8767",
        "response": "Upgrade",
        "votes": 0,
        "class": "DEMONHUNTER",
        "instance": "Amirdrassil, the Dream's Hope-Normal",
        "boss": "Smolderon",
        "gear1": "[Lightning Whelk Axe]",
        "gear2": "[Double Time]",
        "responseID": "1",
        "isAwardReason": "false",
        "rollType": "normal",
        "subType": "Warglaives",
        "equipLoc": "One-Hand",
        "note": "2,4%",
        "owner": "Wojer-Blackrock",
        "itemName": "Remnant Charglaive"
    },
    {
        "player": "Leftêr-Blackrock",
        "date": "15/11/23",
        "time": "20:32:28",
        "id": "1700073148-10",
        "itemID": 207165,
        "itemString": "item:207165::::::::70:72::3:5:6652:7979:9560:1485:8767",
        "response": "Upgrade",
        "votes": 0,
        "class": "DEMONHUNTER",
        "instance": "Amirdrassil, the Dream's Hope-Normal",
        "boss": "Igira the Cruel",
        "gear1": "[Dragonfire Bomb Dispenser]",
        "gear2": "[Elementium Pocket Anvil]",
        "responseID": "1",
        "isAwardReason": "false",
        "rollType": "normal",
        "subType": "Miscellaneous",
        "equipLoc": "Trinket",
        "note": "3,38% Upgrade",
        "owner": "Wojer-Blackrock",
        "itemName": "Bandolier of Twisted Blades"
    },
    {
        "player": "Leftêr-Blackrock",
        "date": "15/11/23",
        "time": "21:45:35",
        "id": "1700077535-31",
        "itemID": 207474,
        "itemString": "item:207474::::::::70:72::3:4:9512:7979:1491:8767",
        "response": "Upgrade",
        "votes": 0,
        "class": "DEMONHUNTER",
        "instance": "Amirdrassil, the Dream's Hope-Normal",
        "boss": "Larodar, Keeper of the Flame",
        "gear1": "[Life-Bound Trousers |A:Professions-ChatIcon-Quality-Tier5:17:17::1|a]",
        "gear2": "",
        "responseID": "1",
        "isAwardReason": "false",
        "rollType": "normal",
        "subType": "Junk",
        "equipLoc": "",
        "note": "1 Set 0,2%",
        "owner": "Wojer-Blackrock",
        "itemName": "Dreadful Ashen Dreamheart"
    },
    {
        "player": "Leftêr-Blackrock",
        "date": "15/11/23",
        "time": "21:46:48",
        "id": "1700077608-32",
        "itemID": 207129,
        "itemString": "item:207129::::::::70:72::3:6:6652:9505:7979:9562:1491:8767",
        "response": "Upgrade",
        "votes": 0,
        "class": "DEMONHUNTER",
        "instance": "Amirdrassil, the Dream's Hope-Normal",
        "boss": "Larodar, Keeper of the Flame",
        "gear1": "[Kinslayer's Vest]",
        "gear2": "",
        "responseID": "1",
        "isAwardReason": "false",
        "rollType": "normal",
        "subType": "Leather",
        "equipLoc": "Chest",
        "note": "1 Set Cata with Legs 2 Set",
        "owner": "Wojer-Blackrock",
        "itemName": "Robes of the Ashen Grove"
    },
    {
        "player": "Leftêr-Blackrock",
        "date": "15/11/23",
        "time": "22:00:47",
        "id": "1700078447-37",
        "itemID": 207791,
        "itemString": "item:207791::::::::70:72::3:5:6652:7979:9562:1491:8767",
        "response": "Upgrade",
        "votes": 0,
        "class": "DEMONHUNTER",
        "instance": "Amirdrassil, the Dream's Hope-Normal",
        "boss": "Smolderon",
        "gear1": "[Bile-Stained Crawg Tusks]",
        "gear2": "[Double Time]",
        "responseID": "1",
        "isAwardReason": "false",
        "rollType": "normal",
        "subType": "Warglaives",
        "equipLoc": "One-Hand",
        "note": "3,8% Upgrade",
        "owner": "Wojer-Blackrock",
        "itemName": "Remnant Charglaive"
    },
    {
        "player": "Scammerin-Blackrock",
        "date": "15/11/23",
        "time": "20:31:47",
        "id": "1700073107-9",
        "itemID": 207783,
        "itemString": "item:207783::::::::70:72::3:5:6652:7979:9560:1485:8767",
        "response": "Upgrade",
        "votes": 0,
        "class": "ROGUE",
        "instance": "Amirdrassil, the Dream's Hope-Normal",
        "boss": "Igira the Cruel",
        "gear1": "[Primal Molten Shortblade |A:Professions-ChatIcon-Quality-Tier5:17:17::1|a]",
        "gear2": "[Primal Molten Shortblade |A:Professions-ChatIcon-Quality-Tier5:17:17::1|a]",
        "responseID": "1",
        "isAwardReason": "false",
        "rollType": "normal",
        "subType": "Daggers",
        "equipLoc": "One-Hand",
        "note": "6,17",
        "owner": "Wojer-Blackrock",
        "itemName": "Cruel Dreamcarver"
    },
    {
        "player": "Scammerin-Blackrock",
        "date": "15/11/23",
        "time": "22:02:57",
        "id": "1700078577-41",
        "itemID": 207167,
        "itemString": "item:207167::::::::70:72::3:5:41:7979:9562:1491:8767",
        "response": "Upgrade",
        "votes": 0,
        "class": "ROGUE",
        "instance": "Amirdrassil, the Dream's Hope-Normal",
        "boss": "Smolderon",
        "gear1": "[Spiked Counterweight]",
        "gear2": "[Dragonfire Bomb Dispenser]",
        "responseID": "1",
        "isAwardReason": "false",
        "rollType": "normal",
        "subType": "Miscellaneous",
        "equipLoc": "Trinket",
        "note": "7,39 a trinket",
        "owner": "Wojer-Blackrock",
        "itemName": "Ashes of the Embersoul"
    },
    {
        "player": "Arzuria-Blackrock",
        "date": "15/11/23",
        "time": "20:29:53",
        "id": "1700072993-5",
        "itemID": 207469,
        "itemString": "item:207469::::::::70:72::3:4:9514:7979:1485:8767",
        "response": "Upgrade",
        "votes": 0,
        "class": "MONK",
        "instance": "Amirdrassil, the Dream's Hope-Normal",
        "boss": "Igira the Cruel",
        "gear1": "[Fists of the Vermillion Forge]",
        "gear2": "",
        "responseID": "1",
        "isAwardReason": "false",
        "rollType": "normal",
        "subType": "Junk",
        "equipLoc": "",
        "note": "",
        "owner": "Wojer-Blackrock",
        "itemName": "Zenith Tormented Dreamheart"
    },
    {
        "player": "Beefbote-Blackrock",
        "date": "15/11/23",
        "time": "22:01:37",
        "id": "1700078497-40",
        "itemID": 207161,
        "itemString": "item:207161::::::::70:72::3:6:6652:9505:7979:9562:1491:8767",
        "response": "Upgrade",
        "votes": 0,
        "class": "HUNTER",
        "instance": "Amirdrassil, the Dream's Hope-Normal",
        "boss": "Smolderon",
        "gear1": "[Voice of the Silent Star]",
        "gear2": "",
        "responseID": "1",
        "isAwardReason": "false",
        "rollType": "normal",
        "subType": "Cloth",
        "equipLoc": "Back",
        "note": "",
        "owner": "Wojer-Blackrock",
        "itemName": "Mantle of Blazing Sacrifice"
    },
    {
        "player": "Mokielock-Blackrock",
        "date": "15/11/23",
        "time": "21:01:57",
        "id": "1700074917-17",
        "itemID": 207462,
        "itemString": "item:207462::::::::70:72::3:3:7979:1491:8767",
        "response": "Upgrade",
        "votes": 0,
        "class": "WARLOCK",
        "instance": "Amirdrassil, the Dream's Hope-Normal",
        "boss": "Nymue, Weaver of the Cycle",
        "gear1": "[Cursed Robes of the Sinister Savant]",
        "gear2": "",
        "responseID": "1",
        "isAwardReason": "false",
        "rollType": "normal",
        "subType": "Junk",
        "equipLoc": "",
        "note": "",
        "owner": "Wojer-Blackrock",
        "itemName": "Dreadful Verdurous Dreamheart"
    },
    {
        "player": "Mokielock-Blackrock",
        "date": "15/11/23",
        "time": "22:28:24",
        "id": "1700080104-46",
        "itemID": 207795,
        "itemString": "item:207795::::::::70:72::3:5:6652:7979:9563:1494:8767",
        "response": "Upgrade",
        "votes": 0,
        "class": "WARLOCK",
        "instance": "Amirdrassil, the Dream's Hope-Normal",
        "boss": "Tindral Sageswift, Seer of the Flame",
        "gear1": "[Illuminating Pillar of the Isles |A:Professions-ChatIcon-Quality-Tier5:17:17::1|a]",
        "gear2": "",
        "responseID": "1",
        "isAwardReason": "false",
        "rollType": "normal",
        "subType": "Staves",
        "equipLoc": "Two-Hand",
        "note": "7%",
        "owner": "Wojer-Blackrock",
        "itemName": "Eternal Kindler's Greatstaff"
    },
    {
        "player": "Rhiinfistn-Blackrock",
        "date": "15/11/23",
        "time": "20:47:38",
        "id": "1700074058-15",
        "itemID": 207127,
        "itemString": "item:207127::::::::70:72::3:6:42:9505:7979:9561:1488:8767",
        "response": "Upgrade",
        "votes": 0,
        "class": "MONK",
        "instance": "Amirdrassil, the Dream's Hope-Normal",
        "boss": "Council of Dreams",
        "gear1": "[Spines of the Vermillion Forge]",
        "gear2": "",
        "responseID": "1",
        "isAwardReason": "false",
        "rollType": "normal",
        "subType": "Leather",
        "equipLoc": "Shoulder",
        "note": "-1,6 % wegen set",
        "owner": "Wojer-Blackrock",
        "itemName": "Strigine Epaulets"
    },
    {
        "player": "Rhiinfistn-Blackrock",
        "date": "15/11/23",
        "time": "21:23:55",
        "id": "1700076235-29",
        "itemID": 207128,
        "itemString": "item:207128::::::::70:72::3:7:6652:9599:9505:7979:9561:1488:8767",
        "response": "Upgrade",
        "votes": 0,
        "class": "MONK",
        "instance": "Amirdrassil, the Dream's Hope-Normal",
        "boss": "Volcoross",
        "gear1": "[Chronomancer's Stasis Shackles]",
        "gear2": "",
        "responseID": "1",
        "isAwardReason": "false",
        "rollType": "normal",
        "subType": "Leather",
        "equipLoc": "Wrist",
        "note": "1,6",
        "owner": "Wojer-Blackrock",
        "itemName": "Primordial Serpent's Bindings"
    },
    {
        "player": "Merith-Blackrock",
        "date": "15/11/23",
        "time": "20:27:32",
        "id": "1700072852-3",
        "itemID": 207153,
        "itemString": "item:207153::::::::70:72::3:6:6652:9505:7979:9560:1485:8767",
        "response": "Pass",
        "votes": 0,
        "class": "PALADIN",
        "instance": "Amirdrassil, the Dream's Hope-Normal",
        "boss": "Igira the Cruel",
        "gear1": "[Heartfire Sentinel's Faulds]",
        "gear2": "",
        "responseID": "PASS",
        "isAwardReason": "false",
        "rollType": "normal",
        "subType": "Plate",
        "equipLoc": "Legs",
        "note": "",
        "owner": "Wojer-Blackrock",
        "itemName": "Seared Ironwood Greaves"
    },
    {
        "player": "Merith-Blackrock",
        "date": "15/11/23",
        "time": "20:45:43",
        "id": "1700073943-12",
        "itemID": 210205,
        "itemString": "item:210205::::::::70:72::3:7:43:9599:9505:7979:9561:1488:8767",
        "response": "Upgrade",
        "votes": 0,
        "class": "PALADIN",
        "instance": "Amirdrassil, the Dream's Hope-Normal",
        "boss": "Council of Dreams",
        "gear1": "[Bonds of Desperate Ascension]",
        "gear2": "",
        "responseID": "1",
        "isAwardReason": "false",
        "rollType": "normal",
        "subType": "Plate",
        "equipLoc": "Wrist",
        "note": "17%",
        "owner": "Wojer-Blackrock",
        "itemName": "Vigilant Protector's Bracers"
    },
    {
        "player": "Iysform-Blackrock",
        "date": "15/11/23",
        "time": "20:33:04",
        "id": "1700073184-11",
        "itemID": 207169,
        "itemString": "item:207169::::::::70:72::3:5:6652:7979:9560:1485:8767",
        "response": "Upgrade",
        "votes": 0,
        "class": "PALADIN",
        "instance": "Amirdrassil, the Dream's Hope-Normal",
        "boss": "Igira the Cruel",
        "gear1": "[Elementium Pocket Anvil]",
        "gear2": "[Ominous Chromatic Essence]",
        "responseID": "1",
        "isAwardReason": "false",
        "rollType": "normal",
        "subType": "Miscellaneous",
        "equipLoc": "Trinket",
        "note": "",
        "owner": "Wojer-Blackrock",
        "itemName": "Branch of the Tormented Ancient"
    },
    {
        "player": "Iysform-Blackrock",
        "date": "15/11/23",
        "time": "21:19:17",
        "id": "1700075957-27",
        "itemID": 207148,
        "itemString": "item:207148::::::::70:72::3:6:6652:9505:7979:9561:1488:8767",
        "response": "Upgrade",
        "votes": 0,
        "class": "PALADIN",
        "instance": "Amirdrassil, the Dream's Hope-Normal",
        "boss": "Volcoross",
        "gear1": "[Primal Molten Sabatons |A:Professions-ChatIcon-Quality-Tier5:17:17::1|a]",
        "gear2": "",
        "responseID": "1",
        "isAwardReason": "false",
        "rollType": "normal",
        "subType": "Plate",
        "equipLoc": "Feet",
        "note": "0,3",
        "owner": "Wojer-Blackrock",
        "itemName": "Lavaforged Sollerets"
    },
    {
        "player": "Iysform-Blackrock",
        "date": "15/11/23",
        "time": "22:00:57",
        "id": "1700078457-39",
        "itemID": 207155,
        "itemString": "item:207155::::::::70:72::3:6:6652:9505:7979:9562:1491:8767",
        "response": "Upgrade",
        "votes": 0,
        "class": "PALADIN",
        "instance": "Amirdrassil, the Dream's Hope-Normal",
        "boss": "Smolderon",
        "gear1": "[Sharktooth-Knuckled Grips]",
        "gear2": "",
        "responseID": "1",
        "isAwardReason": "false",
        "rollType": "normal",
        "subType": "Plate",
        "equipLoc": "Hands",
        "note": "1.1",
        "owner": "Wojer-Blackrock",
        "itemName": "Eldermoss Gauntlets"
    },
    {
        "player": "Iysform-Blackrock",
        "date": "15/11/23",
        "time": "22:35:37",
        "id": "1700080537-50",
        "itemID": 207152,
        "itemString": "item:207152::::::::70:72::3:6:6652:9505:7979:9561:1488:8767",
        "response": "Transmog",
        "votes": 0,
        "class": "PALADIN",
        "instance": "Amirdrassil, the Dream's Hope-Normal",
        "boss": "Tindral Sageswift, Seer of the Flame",
        "gear1": "[Heartfire Sentinel's Steelwings]",
        "gear2": "",
        "responseID": "5",
        "isAwardReason": "false",
        "rollType": "normal",
        "subType": "Plate",
        "equipLoc": "Shoulder",
        "note": "",
        "owner": "Wojer-Blackrock",
        "itemName": "Volcanic Spelunker's Vents"
    },
    {
        "player": "Oonah-Blackrock",
        "date": "15/11/23",
        "time": "20:30:35",
        "id": "1700073035-6",
        "itemID": 207794,
        "itemString": "item:207794::::::::70:72::3:5:6652:7979:9560:1485:8767",
        "response": "Upgrade",
        "votes": 0,
        "class": "PRIEST",
        "instance": "Amirdrassil, the Dream's Hope-Normal",
        "boss": "Igira the Cruel",
        "gear1": "[Primal Molten Spellblade |A:Professions-ChatIcon-Quality-Tier5:17:17::1|a]",
        "gear2": "[Echo's Maddening Volume]",
        "responseID": "1",
        "isAwardReason": "false",
        "rollType": "normal",
        "subType": "Staves",
        "equipLoc": "Two-Hand",
        "note": "9%",
        "owner": "Wojer-Blackrock",
        "itemName": "Staff of Incandescent Torment"
    },
    {
        "player": "Yabajín-Blackrock",
        "date": "15/11/23",
        "time": "20:31:42",
        "id": "1700073102-8",
        "itemID": 207126,
        "itemString": "item:207126::::::::70:72::3:6:6652:9505:7979:9560:1485:8767",
        "response": "Upgrade",
        "votes": 0,
        "class": "MONK",
        "instance": "Amirdrassil, the Dream's Hope-Normal",
        "boss": "Igira the Cruel",
        "gear1": "[Ancient Rotwalkers]",
        "gear2": "",
        "responseID": "1",
        "isAwardReason": "false",
        "rollType": "normal",
        "subType": "Leather",
        "equipLoc": "Feet",
        "note": "+1,31%",
        "owner": "Wojer-Blackrock",
        "itemName": "Twisted Blossom Stompers"
    },
    {
        "player": "Plaguerunner-Blackrock",
        "date": "15/11/23",
        "time": "21:04:10",
        "id": "1700075050-23",
        "itemID": 210203,
        "itemString": "item:210203::::::::70:72::3:7:6652:9599:9505:7979:9562:1491:8767",
        "response": "Upgrade",
        "votes": 0,
        "class": "HUNTER",
        "instance": "Amirdrassil, the Dream's Hope-Normal",
        "boss": "Nymue, Weaver of the Cycle",
        "gear1": "[Flame-Touched Cuffs |A:Professions-ChatIcon-Quality-Tier5:17:17::1|a]",
        "gear2": "",
        "responseID": "1",
        "isAwardReason": "false",
        "rollType": "normal",
        "subType": "Mail",
        "equipLoc": "Wrist",
        "note": "0.92%",
        "owner": "Wojer-Blackrock",
        "itemName": "Wellspring Wristlets"
    },
    {
        "player": "Plaguerunner-Blackrock",
        "date": "15/11/23",
        "time": "22:29:23",
        "id": "1700080163-47",
        "itemID": 207137,
        "itemString": "item:207137::::::::70:72::3:6:6652:9505:7979:9563:1494:8767",
        "response": "Upgrade",
        "votes": 0,
        "class": "HUNTER",
        "instance": "Amirdrassil, the Dream's Hope-Normal",
        "boss": "Tindral Sageswift, Seer of the Flame",
        "gear1": "[Ashen Predator's Skinners]",
        "gear2": "",
        "responseID": "1",
        "isAwardReason": "false",
        "rollType": "normal",
        "subType": "Mail",
        "equipLoc": "Hands",
        "note": "off-set slot",
        "owner": "Wojer-Blackrock",
        "itemName": "Flameseer's Winged Grasps"
    },
    {
        "player": "Gingaer-Blackrock",
        "date": "15/11/23",
        "time": "20:27:24",
        "id": "1700072844-2",
        "itemID": 207153,
        "itemString": "item:207153::::::::70:72::3:6:40:9505:7979:9560:1485:8767",
        "response": "Upgrade",
        "votes": 0,
        "class": "DEATHKNIGHT",
        "instance": "Amirdrassil, the Dream's Hope-Normal",
        "boss": "Igira the Cruel",
        "gear1": "[Lingering Phantom's Schynbalds]",
        "gear2": "",
        "responseID": "1",
        "isAwardReason": "false",
        "rollType": "normal",
        "subType": "Plate",
        "equipLoc": "Legs",
        "note": "",
        "owner": "Wojer-Blackrock",
        "itemName": "Seared Ironwood Greaves"
    },
    {
        "player": "Gingaer-Blackrock",
        "date": "15/11/23",
        "time": "21:03:41",
        "id": "1700075021-20",
        "itemID": 207155,
        "itemString": "item:207155::::::::70:72::3:6:6652:9505:7979:9562:1491:8767",
        "response": "Upgrade",
        "votes": 0,
        "class": "DEATHKNIGHT",
        "instance": "Amirdrassil, the Dream's Hope-Normal",
        "boss": "Nymue, Weaver of the Cycle",
        "gear1": "[Lingering Phantom's Gauntlets]",
        "gear2": "",
        "responseID": "1",
        "isAwardReason": "false",
        "rollType": "normal",
        "subType": "Plate",
        "equipLoc": "Hands",
        "note": "",
        "owner": "Wojer-Blackrock",
        "itemName": "Eldermoss Gauntlets"
    },
    {
        "player": "Gingaer-Blackrock",
        "date": "15/11/23",
        "time": "21:19:13",
        "id": "1700075953-26",
        "itemID": 207148,
        "itemString": "item:207148::::::::70:72::3:6:6652:9505:7979:9561:1488:8767",
        "response": "Upgrade",
        "votes": 0,
        "class": "DEATHKNIGHT",
        "instance": "Amirdrassil, the Dream's Hope-Normal",
        "boss": "Volcoross",
        "gear1": "[Primal Molten Sabatons |A:Professions-ChatIcon-Quality-Tier5:17:17::1|a]",
        "gear2": "",
        "responseID": "1",
        "isAwardReason": "false",
        "rollType": "normal",
        "subType": "Plate",
        "equipLoc": "Feet",
        "note": "2,5%",
        "owner": "Wojer-Blackrock",
        "itemName": "Lavaforged Sollerets"
    },
    {
        "player": "Gingaer-Blackrock",
        "date": "15/11/23",
        "time": "21:24:35",
        "id": "1700076275-30",
        "itemID": 207152,
        "itemString": "item:207152::::::::70:72::3:6:6652:9505:7979:9561:1488:8767",
        "response": "2-Set",
        "votes": 0,
        "class": "DEATHKNIGHT",
        "instance": "Amirdrassil, the Dream's Hope-Normal",
        "boss": "Volcoross",
        "gear1": "[Lingering Phantom's Shoulderplates]",
        "gear2": "",
        "responseID": "2",
        "isAwardReason": "false",
        "rollType": "normal",
        "subType": "Plate",
        "equipLoc": "Shoulder",
        "note": "+ Catalyst 2er Set",
        "owner": "Wojer-Blackrock",
        "itemName": "Volcanic Spelunker's Vents"
    },
    {
        "player": "Gingaer-Blackrock",
        "date": "15/11/23",
        "time": "22:00:16",
        "id": "1700078416-36",
        "itemID": 207478,
        "itemString": "item:207478::::::::70:72::3:4:9511:7979:1491:8767",
        "response": "2-Set",
        "votes": 0,
        "class": "DEATHKNIGHT",
        "instance": "Amirdrassil, the Dream's Hope-Normal",
        "boss": "Smolderon",
        "gear1": "[Lingering Phantom's Shoulderplates]",
        "gear2": "",
        "responseID": "2",
        "isAwardReason": "false",
        "rollType": "normal",
        "subType": "Junk",
        "equipLoc": "",
        "note": "+Catlyst - kann die NonSet Schultern dann abgeben",
        "owner": "Wojer-Blackrock",
        "itemName": "Dreadful Smoldering Dreamheart"
    },
    {
        "player": "Snusnuu-Blackrock",
        "date": "15/11/23",
        "time": "21:04:59",
        "id": "1700075099-24",
        "itemID": 208616,
        "itemString": "item:208616::::::::70:72::3:6:6652:7979:9563:9418:1494:8767",
        "response": "Upgrade",
        "votes": 0,
        "class": "SHAMAN",
        "instance": "Amirdrassil, the Dream's Hope-Normal",
        "boss": "Nymue, Weaver of the Cycle",
        "gear1": "[Frigid Conservator's Cane]",
        "gear2": "",
        "responseID": "1",
        "isAwardReason": "false",
        "rollType": "normal",
        "subType": "Staves",
        "equipLoc": "Two-Hand",
        "note": "10.1% :ooo",
        "owner": "Wojer-Blackrock",
        "itemName": "Dreambinder, Loom of the Great Cycle"
    },
    {
        "player": "Snusnuu-Blackrock",
        "date": "15/11/23",
        "time": "21:47:57",
        "id": "1700077677-34",
        "itemID": 207143,
        "itemString": "item:207143::::::::70:72::3:7:6652:9600:9505:7979:9562:1491:8767",
        "response": "Upgrade",
        "votes": 0,
        "class": "SHAMAN",
        "instance": "Amirdrassil, the Dream's Hope-Normal",
        "boss": "Larodar, Keeper of the Flame",
        "gear1": "[Raoul's Barrelhook Bracers]",
        "gear2": "",
        "responseID": "1",
        "isAwardReason": "false",
        "rollType": "normal",
        "subType": "Mail",
        "equipLoc": "Wrist",
        "note": "1.83%",
        "owner": "Wojer-Blackrock",
        "itemName": "Twisted Flamecuffs"
    },
    {
        "player": "Dbuff-Blackrock",
        "date": "15/11/23",
        "time": "21:19:33",
        "id": "1700075973-28",
        "itemID": 207146,
        "itemString": "item:207146::::::::70:72::3:7:6652:9599:9505:7979:9561:1488:8767",
        "response": "Upgrade",
        "votes": 0,
        "class": "EVOKER",
        "instance": "Amirdrassil, the Dream's Hope-Normal",
        "boss": "Volcoross",
        "gear1": "[Flame-Touched Chain |A:Professions-ChatIcon-Quality-Tier5:17:17::1|a]",
        "gear2": "",
        "responseID": "1",
        "isAwardReason": "false",
        "rollType": "normal",
        "subType": "Mail",
        "equipLoc": "Waist",
        "note": "",
        "owner": "Wojer-Blackrock",
        "itemName": "Jeweled Sash of the Viper"
    },
    {
        "player": "Garagentor-Blackrock",
        "date": "15/11/23",
        "time": "22:26:50",
        "id": "1700080010-45",
        "itemID": 207473,
        "itemString": "item:207473::::::::70:72::3:4:9513:7979:1494:8767",
        "response": "Upgrade",
        "votes": 0,
        "class": "EVOKER",
        "instance": "Amirdrassil, the Dream's Hope-Normal",
        "boss": "Tindral Sageswift, Seer of the Flame",
        "gear1": "[Crown of Obsidian Secrets]",
        "gear2": "",
        "responseID": "1",
        "isAwardReason": "false",
        "rollType": "normal",
        "subType": "Junk",
        "equipLoc": "",
        "note": "1. Token ",
        "owner": "Wojer-Blackrock",
        "itemName": "Zenith Blazing Dreamheart"
    },
    {
        "player": "Nebuyá-Blackrock",
        "date": "15/11/23",
        "time": "21:04:06",
        "id": "1700075046-22",
        "itemID": 210203,
        "itemString": "item:210203::::::::70:72::3:7:6652:9599:9505:7979:9562:1491:8767",
        "response": "Upgrade",
        "votes": 0,
        "class": "SHAMAN",
        "instance": "Amirdrassil, the Dream's Hope-Normal",
        "boss": "Nymue, Weaver of the Cycle",
        "gear1": "[Flame-Touched Cuffs |A:Professions-ChatIcon-Quality-Tier5:17:17::1|a]",
        "gear2": "",
        "responseID": "1",
        "isAwardReason": "false",
        "rollType": "normal",
        "subType": "Mail",
        "equipLoc": "Wrist",
        "note": "1,0%",
        "owner": "Wojer-Blackrock",
        "itemName": "Wellspring Wristlets"
    },
    {
        "player": "Tanaro-Blackrock",
        "date": "15/11/23",
        "time": "22:31:13",
        "id": "1700080273-48",
        "itemID": 207172,
        "itemString": "item:207172::::::::70:72::3:5:6652:7979:9563:1494:8767",
        "response": "Upgrade",
        "votes": 0,
        "class": "MAGE",
        "instance": "Amirdrassil, the Dream's Hope-Normal",
        "boss": "Tindral Sageswift, Seer of the Flame",
        "gear1": "[Idol of Pure Decay]",
        "gear2": "[Ominous Chromatic Essence]",
        "responseID": "1",
        "isAwardReason": "false",
        "rollType": "normal",
        "subType": "Miscellaneous",
        "equipLoc": "Trinket",
        "note": "+4,1% - BIS",
        "owner": "Wojer-Blackrock",
        "itemName": "Belor'relos, the Suncaller"
    },
    {
        "player": "Olympea-Blackrock",
        "date": "15/11/23",
        "time": "21:17:45",
        "id": "1700075865-25",
        "itemID": 207121,
        "itemString": "item:207121::::::::70:72::3:6:6652:9505:7979:9561:1488:8767",
        "response": "Upgrade",
        "votes": 0,
        "class": "PRIEST",
        "instance": "Amirdrassil, the Dream's Hope-Normal",
        "boss": "Volcoross",
        "gear1": "[Command of the Furnace Seraph]",
        "gear2": "",
        "responseID": "1",
        "isAwardReason": "false",
        "rollType": "normal",
        "subType": "Cloth",
        "equipLoc": "Chest",
        "note": "disc",
        "owner": "Wojer-Blackrock",
        "itemName": "Vesture of the Smoldering Serpent"
    },
    {
        "player": "Pantlezz-Blackrock",
        "date": "15/11/23",
        "time": "21:47:14",
        "id": "1700077634-33",
        "itemID": 207792,
        "itemString": "item:207792::::::::70:72::3:5:6652:7979:9562:1491:8767",
        "response": "Upgrade",
        "votes": 0,
        "class": "DRUID",
        "instance": "Amirdrassil, the Dream's Hope-Normal",
        "boss": "Larodar, Keeper of the Flame",
        "gear1": "[Obsidian Seared Halberd |A:Professions-ChatIcon-Quality-Tier5:17:17::1|a]",
        "gear2": "",
        "responseID": "1",
        "isAwardReason": "false",
        "rollType": "normal",
        "subType": "Polearms",
        "equipLoc": "Two-Hand",
        "note": "8.3",
        "owner": "Wojer-Blackrock",
        "itemName": "Scythe of the Fallen Keeper"
    },
    {
        "player": "Pantlezz-Blackrock",
        "date": "15/11/23",
        "time": "22:25:47",
        "id": "1700079947-44",
        "itemID": 207471,
        "itemString": "item:207471::::::::70:72::3:4:9513:7979:1494:8767",
        "response": "Upgrade",
        "votes": 0,
        "class": "DRUID",
        "instance": "Amirdrassil, the Dream's Hope-Normal",
        "boss": "Tindral Sageswift, Seer of the Flame",
        "gear1": "[Bough of the Autumn Blaze]",
        "gear2": "",
        "responseID": "1",
        "isAwardReason": "false",
        "rollType": "normal",
        "subType": "Junk",
        "equipLoc": "",
        "note": "bisher 0 pieces",
        "owner": "Wojer-Blackrock",
        "itemName": "Mystic Blazing Dreamheart"
    }
]